jsonservice/__init__.py
jsonservice/jsonservice.py
jsonservice-1.0.0.dist-info/METADATA
jsonservice-1.0.0.dist-info/WHEEL
jsonservice-1.0.0.dist-info/top_level.txt
jsonservice-1.0.0.dist-info/RECORD
